{
  "project_info": {
    "project_number": "2329287643",
    "firebase_url": "https://all-shoping-app-c8025-default-rtdb.asia-southeast1.firebasedatabase.app",
    "project_id": "all-shoping-app-c8025",
    "storage_bucket": "all-shoping-app-c8025.appspot.com"
  },
  "client": [
    {
      "client_info": {
        "mobilesdk_app_id": "1:2329287643:android:c12017e389d7a6309825fe",
        "android_client_info": {
          "package_name": "com.allshopping.admin"
        }
      },
      "oauth_client": [
        {
          "client_id": "2329287643-h5f932md881nqsdi13e88kb9vmuc1di7.apps.googleusercontent.com",
          "client_type": 1,
          "android_info": {
            "package_name": "com.allshopping.admin",
            "certificate_hash": "2449df862bf3c1d4438582c9f19af26fca0e5f17"
          }
        },
        {
          "client_id": "2329287643-vq1kmdog5h09s9odt8dko7f1mni918r9.apps.googleusercontent.com",
          "client_type": 3
        }
      ],
      "api_key": [
        {
          "current_key": "AIzaSyAb808-kA_FrdvHYRXLHPtee7COvVpiTUc"
        }
      ],
      "services": {
        "appinvite_service": {
          "other_platform_oauth_client": [
            {
              "client_id": "2329287643-8v904j0kqpof13b6g89b136e9t10ltfi.apps.googleusercontent.com",
              "client_type": 3
            }
          ]
        }
      }
    },
    {
      "client_info": {
        "mobilesdk_app_id": "1:2329287643:android:fdffe4fbb23c50389825fe",
        "android_client_info": {
          "package_name": "com.allshopping.app"
        }
      },
      "oauth_client": [
        {
          "client_id": "2329287643-vq1kmdog5h09s9odt8dko7f1mni918r9.apps.googleusercontent.com",
          "client_type": 3
        }
      ],
      "api_key": [
        {
          "current_key": "AIzaSyAb808-kA_FrdvHYRXLHPtee7COvVpiTUc"
        }
      ],
      "services": {
        "appinvite_service": {
          "other_platform_oauth_client": [
            {
              "client_id": "2329287643-8v904j0kqpof13b6g89b136e9t10ltfi.apps.googleusercontent.com",
              "client_type": 3
            }
          ]
        }
      }
    }
  ],
  "configuration_version": "1"
}